{
  "packageRules": [
    {
      "description": "Rook-Ceph image and chart",
      "groupName": "Rook Ceph",
      "matchPackagePatterns": ["rook.ceph"],
      "matchDatasources": ["docker", "helm"],
      "group": { "commitMessageTopic": "{{{groupName}}} group" },
      "separateMinorPatch": true
    },
    {
      "description": "Thanos image and chart versions do not match",
      "groupName": "Thanos",
      "matchPackagePatterns": ["thanos"],
      "matchDatasources": ["docker", "github-releases", "helm"],
      "matchUpdateTypes": ["minor", "patch"],
      "group": { "commitMessageTopic": "{{{groupName}}} group" },
      "stabilityDays": 3,
      "separateMinorPatch": false
    },
    {
      "description": "Vector image and chart versions do not match",
      "groupName": "Vector",
      "matchPackagePatterns": ["vector"],
      "matchDatasources": ["docker", "github-releases", "helm"],
      "matchUpdateTypes": ["minor", "patch"],
      "group": { "commitMessageTopic": "{{{groupName}}} group" },
      "stabilityDays": 3,
      "separateMinorPatch": false
    }
  ]
}
